adsv/__init__.py
adsv/dsv_library.py
adsv/file_utilities.py
adsv/main.py
adsv/string_utilities.py
pnu_adsv-1.0.1.data/data/man/man1/adsv.1.gz
pnu_adsv-1.0.1.dist-info/License
pnu_adsv-1.0.1.dist-info/METADATA
pnu_adsv-1.0.1.dist-info/WHEEL
pnu_adsv-1.0.1.dist-info/entry_points.txt
pnu_adsv-1.0.1.dist-info/top_level.txt
pnu_adsv-1.0.1.dist-info/RECORD
