Metadata-Version: 2.1
Name: pnu-adsv
Version: 1.0.1
Summary: Analyze delimiter-separated values files
Home-page: https://github.com/HubTou/adsv/
Author: Hubert Tournier
Author-email: hubert.tournier@gmail.com
License: BSD 3-Clause License
Project-URL: Bug Tracker, https://github.com/HubTou/adsv/issues
Keywords: pnu-project
Classifier: Development Status :: 5 - Production/Stable
Classifier: Environment :: Console
Classifier: Intended Audience :: Developers
Classifier: Intended Audience :: End Users/Desktop
Classifier: License :: OSI Approved :: BSD License
Classifier: Natural Language :: English
Classifier: Operating System :: OS Independent
Classifier: Operating System :: POSIX :: BSD :: FreeBSD
Classifier: Operating System :: Microsoft :: Windows
Classifier: Programming Language :: Python :: 3
Classifier: Programming Language :: Python :: 3.6
Classifier: Programming Language :: Python :: 3.7
Classifier: Programming Language :: Python :: 3.8
Classifier: Programming Language :: Python :: 3.9
Classifier: Programming Language :: Python :: 3.10
Classifier: Programming Language :: Python :: 3.11
Classifier: Topic :: Software Development :: Libraries :: Python Modules
Classifier: Topic :: System
Classifier: Topic :: Utilities
Requires-Python: >=3.6
License-File: License
Requires-Dist: pnu-libpnu
Requires-Dist: chardet
Requires-Dist: python-dateutil
